{
  "resourceType": "Bundle",
  "id": "examplebundle",
  "type": "collection",
  "entry": [
    {
      "resource": {
        "resourceType": "Patient",
        "id": "test-hiv-patient",
        "meta": {
          "profile": [
            "http://openhie.org/fhir/hiv-casereporting/StructureDefinition/hiv-patient"
          ]
        },
        "text": {
          "status": "generated",
          "div": "<div xmlns=\"http://www.w3.org/1999/xhtml\"><p><b>Generated Narrative</b></p><p><b>identifier</b>: id: 00001</p><p><b>name</b>: Robert , David Smith </p></div>"
        },
        "identifier": [
          {
            "system": "https://basespecs.vn/NamingSystem/ARTIdentifiers",
            "value": "00001"
          }
        ],
        "name": [
          {
            "given": [
              "Robert"
            ]
          },
          {
            "family": "Smith",
            "given": [
              "David"
            ]
          }
        ]
      }
    },
    {
      "resource": {
        "resourceType": "Condition",
        "id": "test-hiv-condition",
        "meta": {
          "profile": [
            "http://openhie.org/fhir/hiv-casereporting/StructureDefinition/hiv-condition"
          ]
        },
        "text": {
          "status": "generated",
          "div": "<div xmlns=\"http://www.w3.org/1999/xhtml\"><p><b>Generated Narrative</b></p><p><b>subject</b>: <a href=\"#Patient_test-hiv-patient\">See above (Patient/test-hiv-patient)</a></p><p><b>recordedDate</b>: 2020-09-09</p></div>"
        },
        "subject": {
          "reference": "Patient/test-hiv-patient"
        },
        "recordedDate": "2020-09-09"
      }
    }
  ]
}